sccmecextractor/__init__.py
sccmecextractor/extract_SCCmec.py
sccmecextractor/locate_att_sites.py
sccmecextractor/locate_att_sites_v2.py
sccmecextractor/locate_att_sites_v3.py
sccmecextractor-1.1.0.dist-info/licenses/LICENSE
sccmecextractor-1.1.0.dist-info/METADATA
sccmecextractor-1.1.0.dist-info/WHEEL
sccmecextractor-1.1.0.dist-info/entry_points.txt
sccmecextractor-1.1.0.dist-info/top_level.txt
sccmecextractor-1.1.0.dist-info/RECORD
