Metadata-Version: 2.4
Name: sccmecextractor
Version: 1.1.0
Summary: A Python toolkit for extracting SCCmec sequences from Staphylococcus whole genome sequences
Author-email: Alison MacFadyen <alison.macfadyen86@gmail.com>
Maintainer-email: Alison MacFadyen <alison.macfadyen86@gmail.com>
License: MIT License
Project-URL: Homepage, https://github.com/AlisonMacFadyen/SCCmecExtractor
Project-URL: Repository, https://github.com/AlisonMacFadyen/SCCmecExtractor
Project-URL: Issues, https://github.com/AlisonMacFadyen/SCCmecExtractor/issues
Project-URL: Documentation, https://github.com/AlisonMacFadyen/SCCmecExtractor#readme
Keywords: bioinformatics,genomics,staphylococcus,sccmec,bacterial-genomics
Classifier: Development Status :: 5 - Production/Stable
Classifier: Intended Audience :: Science/Research
Classifier: Programming Language :: Python :: 3.9
Classifier: Programming Language :: Python :: 3.10
Classifier: Programming Language :: Python :: 3.11
Classifier: Programming Language :: Python :: 3.12
Classifier: Topic :: Scientific/Engineering :: Bio-Informatics
Requires-Python: >=3.9
License-File: LICENSE
Requires-Dist: biopython>=1.85
Provides-Extra: dev
Requires-Dist: pytest>=7.0; extra == "dev"
Requires-Dist: pandas>=2.3.0; extra == "dev"
Requires-Dist: pytest-cov; extra == "dev"
Requires-Dist: black; extra == "dev"
Requires-Dist: flake8; extra == "dev"
Requires-Dist: mypy; extra == "dev"
Dynamic: license-file
